graphpanda/__init__.py
graphpanda/graphpanda.py
graphpanda/to_cypher.py
graphpanda-0.1.0.dist-info/AUTHORS.rst
graphpanda-0.1.0.dist-info/LICENSE
graphpanda-0.1.0.dist-info/METADATA
graphpanda-0.1.0.dist-info/WHEEL
graphpanda-0.1.0.dist-info/top_level.txt
graphpanda-0.1.0.dist-info/RECORD
