Metadata-Version: 2.1
Name: graphpanda
Version: 0.1.0
Summary: It's a python package that allows you to convert pandas dataframe into Cypher insert queries. It gives you a way to specify your record linking algorithms for determining edges and setting attributes.
Home-page: https://github.com/bobrinik/graphpanda
Author: Maksim Bober
License: MIT license
Keywords: graphpanda
Platform: UNKNOWN
Classifier: Development Status :: 2 - Pre-Alpha
Classifier: Intended Audience :: Developers
Classifier: License :: OSI Approved :: MIT License
Classifier: Natural Language :: English
Classifier: Programming Language :: Python :: 3
Classifier: Programming Language :: Python :: 3.5
Classifier: Programming Language :: Python :: 3.6
Classifier: Programming Language :: Python :: 3.7
Classifier: Programming Language :: Python :: 3.8
Requires-Python: >=3.5
